dynamodb_backup.py
dynamodb_backup-0.4.0.dist-info/DESCRIPTION.rst
dynamodb_backup-0.4.0.dist-info/METADATA
dynamodb_backup-0.4.0.dist-info/RECORD
dynamodb_backup-0.4.0.dist-info/WHEEL
dynamodb_backup-0.4.0.dist-info/entry_points.txt
dynamodb_backup-0.4.0.dist-info/metadata.json
dynamodb_backup-0.4.0.dist-info/top_level.txt
dynamodb_backup-0.4.0.dist-info/zip-safe
