Metadata-Version: 2.0
Name: dynamodb-backup
Version: 0.4.0
Summary: Backup a DynamoDB table to an Avro container
Home-page: UNKNOWN
Author: Gavin M. Roy
Author-email: gavinmroy@gmail.com
License: BSD
Platform: UNKNOWN
Classifier: Development Status :: 3 - Alpha
Classifier: Environment :: Console
Classifier: Environment :: No Input/Output (Daemon)
Classifier: Intended Audience :: System Administrators
Classifier: License :: OSI Approved :: BSD License
Classifier: Natural Language :: English
Classifier: Operating System :: MacOS
Classifier: Operating System :: POSIX
Classifier: Operating System :: POSIX :: BSD
Classifier: Operating System :: POSIX :: Linux
Classifier: Operating System :: Unix
Classifier: Programming Language :: Python :: 2
Classifier: Programming Language :: Python :: 2.7
Classifier: Programming Language :: Python :: 3
Classifier: Programming Language :: Python :: 3.4
Classifier: Programming Language :: Python :: 3.5
Classifier: Programming Language :: Python :: Implementation :: CPython
Classifier: Programming Language :: Python :: Implementation :: PyPy
Requires-Dist: boto3 (<1.5,>=1.4.1)
Requires-Dist: coloredlogs (>=5.2,<6)
Requires-Dist: fastavro (>=0.11.0,<1)
Requires-Dist: requests (>=2.12.4,<3)
Provides-Extra: snappy
Requires-Dist: python-snappy (==0.5); extra == 'snappy'
